MANIFEST.in
README.txt
setup.cfg
setup.py
docs/HISTORY.txt
docs/INSTALL.txt
docs/LICENSE.GPL
docs/LICENSE.txt
ityou/__init__.py
ityou.imessage.egg-info/PKG-INFO
ityou.imessage.egg-info/SOURCES.txt
ityou.imessage.egg-info/dependency_links.txt
ityou.imessage.egg-info/entry_points.txt
ityou.imessage.egg-info/namespace_packages.txt
ityou.imessage.egg-info/not-zip-safe
ityou.imessage.egg-info/paster_plugins.txt
ityou.imessage.egg-info/requires.txt
ityou.imessage.egg-info/top_level.txt
ityou/imessage/__init__.py
ityou/imessage/config.py
ityou/imessage/configure.zcml
ityou/imessage/db_tests.py
ityou/imessage/dbapi.py
ityou/imessage/imessage-tracking.pt
ityou/imessage/interfaces.py
ityou/imessage/skins.zcml
ityou/imessage/tests.py
ityou/imessage/translate.sh
ityou/imessage/viewlets.py
ityou/imessage/Extensions/Install.py
ityou/imessage/Extensions/__init__.py
ityou/imessage/browser/__init__.py
ityou/imessage/browser/configure.zcml
ityou/imessage/browser/dialog-overview.py
ityou/imessage/browser/imessage-inbox.py
ityou/imessage/browser/imessage.py
ityou/imessage/browser/images/email.png
ityou/imessage/browser/images/eye-close.png
ityou/imessage/browser/images/ityou-esi-imessage-icon.png
ityou/imessage/browser/images/message-bar.png
ityou/imessage/browser/images/nicEditorIcons.gif
ityou/imessage/browser/images/jquery-ui/ui-bg_flat_0_aaaaaa_40x100.png
ityou/imessage/browser/images/jquery-ui/ui-bg_flat_75_ffffff_40x100.png
ityou/imessage/browser/images/jquery-ui/ui-bg_glass_55_fbf9ee_1x400.png
ityou/imessage/browser/images/jquery-ui/ui-bg_glass_65_ffffff_1x400.png
ityou/imessage/browser/images/jquery-ui/ui-bg_glass_75_dadada_1x400.png
ityou/imessage/browser/images/jquery-ui/ui-bg_glass_75_e6e6e6_1x400.png
ityou/imessage/browser/images/jquery-ui/ui-bg_glass_95_fef1ec_1x400.png
ityou/imessage/browser/images/jquery-ui/ui-bg_highlight-soft_75_cccccc_1x100.png
ityou/imessage/browser/images/jquery-ui/ui-icons_222222_256x240.png
ityou/imessage/browser/images/jquery-ui/ui-icons_2e83ff_256x240.png
ityou/imessage/browser/images/jquery-ui/ui-icons_454545_256x240.png
ityou/imessage/browser/images/jquery-ui/ui-icons_888888_256x240.png
ityou/imessage/browser/images/jquery-ui/ui-icons_cd0a0a_256x240.png
ityou/imessage/browser/javascripts/_autoresize.jquery.min.js
ityou/imessage/browser/javascripts/_imessage-jq.js
