Metadata-Version: 1.1
Name: ityou.imessage
Version: 1.3.1
Summary: Instant Messaging for ITYOU ESI
Home-page: http://www.ityou.de/esi/
Author: ITYOU/LM
Author-email: lm@ityou.de
License: GPL
Keywords: Messaging
Platform: UNKNOWN
Classifier: Framework :: Plone
Classifier: Programming Language :: Python
